{
  "project_info": {
    "project_number": "503331295526",
    "project_id": "art-gallery-3768a",
    "storage_bucket": "art-gallery-3768a.appspot.com"
  },
  "client": [
    {
      "client_info": {
        "mobilesdk_app_id": "1:503331295526:android:21cce9280aa75537d2f1e7",
        "android_client_info": {
          "package_name": "com.example.artgallery"
        }
      },
      "oauth_client": [
        {
          "client_id": "503331295526-r8govuv1deqp7vr09j15san6p453pmpm.apps.googleusercontent.com",
          "client_type": 3
        }
      ],
      "api_key": [
        {
          "current_key": "AIzaSyDD_y4ZO64hOuUWpji9pUkVpDK3rlTnE9E"
        }
      ],
      "services": {
        "appinvite_service": {
          "other_platform_oauth_client": [
            {
              "client_id": "503331295526-r8govuv1deqp7vr09j15san6p453pmpm.apps.googleusercontent.com",
              "client_type": 3
            }
          ]
        }
      }
    }
  ],
  "configuration_version": "1"
}